Metadata-Version: 2.1
Name: swissREFRAME
Version: 1.1.1
Summary: UNKNOWN
Home-page: https://github.com/adal02/swissREFRAME
Author: Tobias Hofmann
Author-email: hofmann.tobias121@gmail.com
License: UNKNOWN
Download-URL: https://github.com/adal02/swissREFRAME/archive/V1.1.1.tar.gz
Keywords: geodesy,geography,swiss,coordinates,transformation
Platform: UNKNOWN
Classifier: Development Status :: 4 - Beta
Classifier: License :: OSI Approved :: MIT License
Classifier: Programming Language :: Python :: 3
Classifier: Operating System :: OS Independent
